{
    "Author": [
        {
            "Author": "\u0418\u043b\u044c\u044f \u0414\u043e\u0440\u043e\u043d\u0447\u0435\u043d\u043a\u043e\u0432",
            "Article URL": "https://arzamas.academy/courses/15/1"
        },
        {
            "Author": "\u0418\u043b\u044c\u044f \u0414\u043e\u0440\u043e\u043d\u0447\u0435\u043d\u043a\u043e\u0432",
            "Article URL": "https://arzamas.academy/courses/15/2"
        },
        {
            "Author": "\u0418\u043b\u044c\u044f \u0414\u043e\u0440\u043e\u043d\u0447\u0435\u043d\u043a\u043e\u0432",
            "Article URL": "https://arzamas.academy/courses/15/3"
        },
        {
            "Author": "\u0418\u043b\u044c\u044f \u0414\u043e\u0440\u043e\u043d\u0447\u0435\u043d\u043a\u043e\u0432",
            "Article URL": "https://arzamas.academy/courses/15/4"
        },
        {
            "Author": "\u0418\u043b\u044c\u044f \u0414\u043e\u0440\u043e\u043d\u0447\u0435\u043d\u043a\u043e\u0432",
            "Article URL": "https://arzamas.academy/courses/15/5"
        },
        {
            "Author": "\u0418\u043b\u044c\u044f \u0414\u043e\u0440\u043e\u043d\u0447\u0435\u043d\u043a\u043e\u0432",
            "Article URL": "https://arzamas.academy/courses/15/6"
        },
        {
            "Author": "\u0418\u043b\u044c\u044f \u0414\u043e\u0440\u043e\u043d\u0447\u0435\u043d\u043a\u043e\u0432",
            "Article URL": "https://arzamas.academy/courses/15/7"
        },
        {
            "Author": "\u0418\u043b\u044c\u044f \u0414\u043e\u0440\u043e\u043d\u0447\u0435\u043d\u043a\u043e\u0432",
            "Article URL": "https://arzamas.academy/courses/15/8"
        },
        {
            "Author": "\u0418\u043b\u044c\u044f \u0414\u043e\u0440\u043e\u043d\u0447\u0435\u043d\u043a\u043e\u0432",
            "Article URL": "https://arzamas.academy/courses/52/1"
        },
        {
            "Author": "\u0418\u043b\u044c\u044f \u0414\u043e\u0440\u043e\u043d\u0447\u0435\u043d\u043a\u043e\u0432",
            "Article URL": "https://arzamas.academy/courses/52/2"
        },
        {
            "Author": "\u0418\u043b\u044c\u044f \u0414\u043e\u0440\u043e\u043d\u0447\u0435\u043d\u043a\u043e\u0432",
            "Article URL": "https://arzamas.academy/courses/52/3"
        },
        {
            "Author": "\u0418\u043b\u044c\u044f \u0414\u043e\u0440\u043e\u043d\u0447\u0435\u043d\u043a\u043e\u0432",
            "Article URL": "https://arzamas.academy/courses/52/4"
        },
        {
            "Author": "\u0418\u043b\u044c\u044f \u0414\u043e\u0440\u043e\u043d\u0447\u0435\u043d\u043a\u043e\u0432",
            "Article URL": "https://arzamas.academy/courses/52/5"
        },
        {
            "Author": "\u0418\u043b\u044c\u044f \u0414\u043e\u0440\u043e\u043d\u0447\u0435\u043d\u043a\u043e\u0432",
            "Article URL": "https://arzamas.academy/courses/52/6"
        },
        {
            "Author": "\u0418\u043b\u044c\u044f \u0414\u043e\u0440\u043e\u043d\u0447\u0435\u043d\u043a\u043e\u0432",
            "Article URL": "https://arzamas.academy/courses/52/7"
        },
        {
            "Author": "\u0418\u043b\u044c\u044f \u0414\u043e\u0440\u043e\u043d\u0447\u0435\u043d\u043a\u043e\u0432",
            "Article URL": "https://arzamas.academy/courses/85/4"
        },
        {
            "Author": "\u0418\u043b\u044c\u044f \u0414\u043e\u0440\u043e\u043d\u0447\u0435\u043d\u043a\u043e\u0432",
            "Article URL": "https://arzamas.academy/materials/249"
        },
        {
            "Author": "\u0418\u043b\u044c\u044f \u0414\u043e\u0440\u043e\u043d\u0447\u0435\u043d\u043a\u043e\u0432",
            "Article URL": "https://arzamas.academy/materials/1065"
        },
        {
            "Author": "\u0418\u043b\u044c\u044f \u0414\u043e\u0440\u043e\u043d\u0447\u0435\u043d\u043a\u043e\u0432",
            "Article URL": "https://arzamas.academy/materials/1089"
        },
        {
            "Author": "\u0418\u043b\u044c\u044f \u0414\u043e\u0440\u043e\u043d\u0447\u0435\u043d\u043a\u043e\u0432",
            "Article URL": "https://arzamas.academy/materials/1366"
        },
        {
            "Author": "\u0418\u043b\u044c\u044f \u0414\u043e\u0440\u043e\u043d\u0447\u0435\u043d\u043a\u043e\u0432",
            "Article URL": "https://arzamas.academy/materials/1468"
        },
        {
            "Author": "\u0418\u043b\u044c\u044f \u0414\u043e\u0440\u043e\u043d\u0447\u0435\u043d\u043a\u043e\u0432",
            "Article URL": "https://arzamas.academy/materials/1469"
        }
    ]
}