{
    "Author": [
        {
            "Author": "\u041d\u0438\u043a\u0438\u0442\u0430 \u041f\u0435\u0442\u0440\u043e\u0432",
            "Article URL": "https://arzamas.academy/courses/14/1"
        },
        {
            "Author": "\u041d\u0438\u043a\u0438\u0442\u0430 \u041f\u0435\u0442\u0440\u043e\u0432",
            "Article URL": "https://arzamas.academy/courses/14/2"
        },
        {
            "Author": "\u041d\u0438\u043a\u0438\u0442\u0430 \u041f\u0435\u0442\u0440\u043e\u0432",
            "Article URL": "https://arzamas.academy/courses/14/3"
        },
        {
            "Author": "\u041d\u0438\u043a\u0438\u0442\u0430 \u041f\u0435\u0442\u0440\u043e\u0432",
            "Article URL": "https://arzamas.academy/courses/14/4"
        },
        {
            "Author": "\u041d\u0438\u043a\u0438\u0442\u0430 \u041f\u0435\u0442\u0440\u043e\u0432",
            "Article URL": "https://arzamas.academy/courses/14/5"
        },
        {
            "Author": "\u041d\u0438\u043a\u0438\u0442\u0430 \u041f\u0435\u0442\u0440\u043e\u0432",
            "Article URL": "https://arzamas.academy/shorts/305/1"
        },
        {
            "Author": "\u041d\u0438\u043a\u0438\u0442\u0430 \u041f\u0435\u0442\u0440\u043e\u0432",
            "Article URL": "https://arzamas.academy/shorts/305/6"
        },
        {
            "Author": "\u041d\u0438\u043a\u0438\u0442\u0430 \u041f\u0435\u0442\u0440\u043e\u0432",
            "Article URL": "https://arzamas.academy/shorts/305/14"
        },
        {
            "Author": "\u041d\u0438\u043a\u0438\u0442\u0430 \u041f\u0435\u0442\u0440\u043e\u0432",
            "Article URL": "https://arzamas.academy/shorts/347/6"
        },
        {
            "Author": "\u041d\u0438\u043a\u0438\u0442\u0430 \u041f\u0435\u0442\u0440\u043e\u0432",
            "Article URL": "https://arzamas.academy/shorts/361/7"
        },
        {
            "Author": "\u041d\u0438\u043a\u0438\u0442\u0430 \u041f\u0435\u0442\u0440\u043e\u0432",
            "Article URL": "https://arzamas.academy/courses/1066/4"
        },
        {
            "Author": "\u041d\u0438\u043a\u0438\u0442\u0430 \u041f\u0435\u0442\u0440\u043e\u0432",
            "Article URL": "https://arzamas.academy/materials/567"
        },
        {
            "Author": "\u041d\u0438\u043a\u0438\u0442\u0430 \u041f\u0435\u0442\u0440\u043e\u0432",
            "Article URL": "https://arzamas.academy/materials/575"
        },
        {
            "Author": "\u041d\u0438\u043a\u0438\u0442\u0430 \u041f\u0435\u0442\u0440\u043e\u0432",
            "Article URL": "https://arzamas.academy/materials/577"
        },
        {
            "Author": "\u041d\u0438\u043a\u0438\u0442\u0430 \u041f\u0435\u0442\u0440\u043e\u0432",
            "Article URL": "https://arzamas.academy/materials/585"
        },
        {
            "Author": "\u041d\u0438\u043a\u0438\u0442\u0430 \u041f\u0435\u0442\u0440\u043e\u0432",
            "Article URL": "https://arzamas.academy/materials/596"
        },
        {
            "Author": "\u041d\u0438\u043a\u0438\u0442\u0430 \u041f\u0435\u0442\u0440\u043e\u0432",
            "Article URL": "https://arzamas.academy/materials/602"
        },
        {
            "Author": "\u041d\u0438\u043a\u0438\u0442\u0430 \u041f\u0435\u0442\u0440\u043e\u0432",
            "Article URL": "https://arzamas.academy/materials/764"
        },
        {
            "Author": "\u041d\u0438\u043a\u0438\u0442\u0430 \u041f\u0435\u0442\u0440\u043e\u0432",
            "Article URL": "https://arzamas.academy/materials/1672"
        },
        {
            "Author": "\u041d\u0438\u043a\u0438\u0442\u0430 \u041f\u0435\u0442\u0440\u043e\u0432",
            "Article URL": "https://arzamas.academy/materials/1673"
        },
        {
            "Author": "\u041d\u0438\u043a\u0438\u0442\u0430 \u041f\u0435\u0442\u0440\u043e\u0432",
            "Article URL": "https://arzamas.academy/materials/1674"
        },
        {
            "Author": "\u041d\u0438\u043a\u0438\u0442\u0430 \u041f\u0435\u0442\u0440\u043e\u0432",
            "Article URL": "https://arzamas.academy/materials/1682"
        }
    ]
}